setup.py
dmath/__init__.py
dmath/tests.py
dmath.egg-info/PKG-INFO
dmath.egg-info/SOURCES.txt
dmath.egg-info/dependency_links.txt
dmath.egg-info/top_level.txt
